charmlibs/interfaces/tls_certificates/__init__.py
charmlibs/interfaces/tls_certificates/_tls_certificates.py
charmlibs/interfaces/tls_certificates/_version.py
charmlibs/interfaces/tls_certificates/py.typed
charmlibs_interfaces_tls_certificates-1.3.0.dist-info/METADATA
charmlibs_interfaces_tls_certificates-1.3.0.dist-info/WHEEL
charmlibs_interfaces_tls_certificates-1.3.0.dist-info/RECORD
