Metadata-Version: 2.4
Name: charmlibs-interfaces-tls_certificates
Version: 1.3.0
Summary: The charmlibs.interfaces.tls_certificates package.
Project-URL: Repository, https://github.com/canonical/charmlibs
Project-URL: Issues, https://github.com/canonical/charmlibs/issues
Author: The TLS team at Canonical
Classifier: Development Status :: 5 - Production/Stable
Classifier: Intended Audience :: Developers
Classifier: License :: OSI Approved :: Apache Software License
Classifier: Operating System :: POSIX :: Linux
Classifier: Programming Language :: Python :: 3
Requires-Python: >=3.10
Requires-Dist: cryptography>=43.0.0
Requires-Dist: ops
Requires-Dist: pydantic
